fontencrypt/__init__.py
fontencrypt/generate/__init__.py
fontencrypt/generate/conf.py
fontencrypt/generate/fit.py
fontencrypt/generate/gen.py
fontencrypt-0.1.1.dist-info/LICENSE
fontencrypt-0.1.1.dist-info/METADATA
fontencrypt-0.1.1.dist-info/WHEEL
fontencrypt-0.1.1.dist-info/top_level.txt
fontencrypt-0.1.1.dist-info/RECORD
