Metadata-Version: 2.1
Name: fontencrypt
Version: 0.1.1
Summary: 一个由Python实现的字体加密库(反爬)
Home-page: https://github.com/ggdream/fontencrypt
Author: gdream@126.com
License: UNKNOWN
Platform: UNKNOWN
Requires-Dist: fonttools (>=4.0.0)
